embedded/__init__.py
embedded/cli.py
embedded/compiler.py
embedded/build/__init__.py
embedded/build/meson.py
embedded/build/ninja.py
embedded/cpu/__init__.py
embedded/cpu/arm.py
embedded/cpu/riscv.py
embedded/microcontroller/__init__.py
embedded_build-0.0.2.dist-info/LICENSE
embedded_build-0.0.2.dist-info/WHEEL
embedded_build-0.0.2.dist-info/METADATA
embedded_build-0.0.2.dist-info/RECORD
