Metadata-Version: 2.1
Name: embedded-build
Version: 0.0.2
Summary: Python toolkit for building (aka compiling and linking) embedded projects
Author-email: Scott Shawcroft <scott@tannewt.org>
Classifier: License :: OSI Approved :: MIT License
Project-URL: Home, https://embedded.build
